MANIFEST.in
README.md
setup.py
id_card_extractor/__init__.py
id_card_extractor/detect_neat_image.py
id_card_extractor/extractor.py
id_card_extractor/id_card_detection_directory.py
id_card_extractor.egg-info/PKG-INFO
id_card_extractor.egg-info/SOURCES.txt
id_card_extractor.egg-info/dependency_links.txt
id_card_extractor.egg-info/top_level.txt
id_card_extractor/data/labelmap.pbtxt
id_card_extractor/model/frozen_inference_graph.pb
id_card_extractor/utils_extractor/__init__.py
id_card_extractor/utils_extractor/label_map_util.py
id_card_extractor/utils_extractor/visualization_utils.py