Metadata-Version: 2.1
Name: id-card-extractor
Version: 1.1.9
Summary: Crop id card from an image using OpenCV
Home-page: https://github.com/aqua-regia/id-card-detector
Author: Syed Hassan Ashraf
Author-email: hassanashraf8888@gmail.com
License: MIT
Platform: UNKNOWN
Classifier: License :: OSI Approved :: MIT License
Classifier: Programming Language :: Python :: 3
